{"frames":{"gt_0":{"frame":{"x":0,"y":0,"w":32,"h":32},"rotated":false,"trimmed":false,"spriteSourceSize":{"x":0,"y":0,"w":32,"h":32},"sourceSize":{"w":32,"h":32}},"gt_1":{"frame":{"x":32,"y":0,"w":32,"h":32},"rotated":false,"trimmed":false,"spriteSourceSize":{"x":0,"y":0,"w":32,"h":32},"sourceSize":{"w":32,"h":32}},"gt_2":{"frame":{"x":64,"y":0,"w":32,"h":32},"rotated":false,"trimmed":false,"spriteSourceSize":{"x":0,"y":0,"w":32,"h":32},"sourceSize":{"w":32,"h":32}},"gt_3":{"frame":{"x":96,"y":0,"w":32,"h":32},"rotated":false,"trimmed":false,"spriteSourceSize":{"x":0,"y":0,"w":32,"h":32},"sourceSize":{"w":32,"h":32}},"gt_4":{"frame":{"x":128,"y":0,"w":32,"h":32},"rotated":false,"trimmed":false,"spriteSourceSize":{"x":0,"y":0,"w":32,"h":32},"sourceSize":{"w":32,"h":32}},"gt_5":{"frame":{"x":160,"y":0,"w":32,"h":32},"rotated":false,"trimmed":false,"spriteSourceSize":{"x":0,"y":0,"w":32,"h":32},"sourceSize":{"w":32,"h":32}},"gt_6":{"frame":{"x":192,"y":0,"w":32,"h":32},"rotated":false,"trimmed":false,"spriteSourceSize":{"x":0,"y":0,"w":32,"h":32},"sourceSize":{"w":32,"h":32}},"gt_7":{"frame":{"x":224,"y":0,"w":32,"h":32},"rotated":false,"trimmed":false,"spriteSourceSize":{"x":0,"y":0,"w":32,"h":32},"sourceSize":{"w":32,"h":32}},"bt_0":{"frame":{"x":0,"y":32,"w":32,"h":32},"rotated":false,"trimmed":false,"spriteSourceSize":{"x":0,"y":0,"w":32,"h":32},"sourceSize":{"w":32,"h":32}},"bt_1":{"frame":{"x":32,"y":32,"w":32,"h":32},"rotated":false,"trimmed":false,"spriteSourceSize":{"x":0,"y":0,"w":32,"h":32},"sourceSize":{"w":32,"h":32}},"bt_2":{"frame":{"x":64,"y":32,"w":32,"h":32},"rotated":false,"trimmed":false,"spriteSourceSize":{"x":0,"y":0,"w":32,"h":32},"sourceSize":{"w":32,"h":32}},"bt_3":{"frame":{"x":96,"y":32,"w":32,"h":32},"rotated":false,"trimmed":false,"spriteSourceSize":{"x":0,"y":0,"w":32,"h":32},"sourceSize":{"w":32,"h":32}},"bt_4":{"frame":{"x":128,"y":32,"w":32,"h":32},"rotated":false,"trimmed":false,"spriteSourceSize":{"x":0,"y":0,"w":32,"h":32},"sourceSize":{"w":32,"h":32}},"bt_5":{"frame":{"x":160,"y":32,"w":32,"h":32},"rotated":false,"trimmed":false,"spriteSourceSize":{"x":0,"y":0,"w":32,"h":32},"sourceSize":{"w":32,"h":32}},"bt_6":{"frame":{"x":192,"y":32,"w":32,"h":32},"rotated":false,"trimmed":false,"spriteSourceSize":{"x":0,"y":0,"w":32,"h":32},"sourceSize":{"w":32,"h":32}},"bt_7":{"frame":{"x":224,"y":32,"w":32,"h":32},"rotated":false,"trimmed":false,"spriteSourceSize":{"x":0,"y":0,"w":32,"h":32},"sourceSize":{"w":32,"h":32}},"gt_gun_1":{"frame":{"x":0,"y":64,"w":32,"h":32},"rotated":false,"trimmed":false,"spriteSourceSize":{"x":0,"y":0,"w":32,"h":32},"sourceSize":{"w":32,"h":32}},"bt_gun_1":{"frame":{"x":32,"y":64,"w":32,"h":32},"rotated":false,"trimmed":false,"spriteSourceSize":{"x":0,"y":0,"w":32,"h":32},"sourceSize":{"w":32,"h":32}},"big_bullet":{"frame":{"x":64,"y":64,"w":32,"h":32},"rotated":false,"trimmed":false,"spriteSourceSize":{"x":0,"y":0,"w":32,"h":32},"sourceSize":{"w":32,"h":32}},"boom_0":{"frame":{"x":96,"y":64,"w":32,"h":32},"rotated":false,"trimmed":false,"spriteSourceSize":{"x":0,"y":0,"w":32,"h":32},"sourceSize":{"w":32,"h":32}},"boom_1":{"frame":{"x":128,"y":64,"w":32,"h":32},"rotated":false,"trimmed":false,"spriteSourceSize":{"x":0,"y":0,"w":32,"h":32},"sourceSize":{"w":32,"h":32}},"boom_2":{"frame":{"x":160,"y":64,"w":32,"h":32},"rotated":false,"trimmed":false,"spriteSourceSize":{"x":0,"y":0,"w":32,"h":32},"sourceSize":{"w":32,"h":32}},"damage_0":{"frame":{"x":192,"y":64,"w":32,"h":32},"rotated":false,"trimmed":false,"spriteSourceSize":{"x":0,"y":0,"w":32,"h":32},"sourceSize":{"w":32,"h":32}},"damage_1":{"frame":{"x":224,"y":64,"w":32,"h":32},"rotated":false,"trimmed":false,"spriteSourceSize":{"x":0,"y":0,"w":32,"h":32},"sourceSize":{"w":32,"h":32}},"damage_2":{"frame":{"x":256,"y":64,"w":32,"h":32},"rotated":false,"trimmed":false,"spriteSourceSize":{"x":0,"y":0,"w":32,"h":32},"sourceSize":{"w":32,"h":32}},"damage_3":{"frame":{"x":288,"y":64,"w":32,"h":32},"rotated":false,"trimmed":false,"spriteSourceSize":{"x":0,"y":0,"w":32,"h":32},"sourceSize":{"w":32,"h":32}},"gt_gun_2":{"frame":{"x":0,"y":96,"w":32,"h":32},"rotated":false,"trimmed":false,"spriteSourceSize":{"x":0,"y":0,"w":32,"h":32},"sourceSize":{"w":32,"h":32}},"bt_gun_2":{"frame":{"x":32,"y":96,"w":32,"h":32},"rotated":false,"trimmed":false,"spriteSourceSize":{"x":0,"y":0,"w":32,"h":32},"sourceSize":{"w":32,"h":32}},"health_0":{"frame":{"x":64,"y":96,"w":32,"h":32},"rotated":false,"trimmed":false,"spriteSourceSize":{"x":0,"y":0,"w":32,"h":32},"sourceSize":{"w":32,"h":32}},"health_2":{"frame":{"x":96,"y":96,"w":32,"h":32},"rotated":false,"trimmed":false,"spriteSourceSize":{"x":0,"y":0,"w":32,"h":32},"sourceSize":{"w":32,"h":32}},"health_4":{"frame":{"x":128,"y":96,"w":32,"h":32},"rotated":false,"trimmed":false,"spriteSourceSize":{"x":0,"y":0,"w":32,"h":32},"sourceSize":{"w":32,"h":32}},"health_6":{"frame":{"x":160,"y":96,"w":32,"h":32},"rotated":false,"trimmed":false,"spriteSourceSize":{"x":0,"y":0,"w":32,"h":32},"sourceSize":{"w":32,"h":32}},"damage_4":{"frame":{"x":192,"y":96,"w":32,"h":32},"rotated":false,"trimmed":false,"spriteSourceSize":{"x":0,"y":0,"w":32,"h":32},"sourceSize":{"w":32,"h":32}},"damage_5":{"frame":{"x":224,"y":96,"w":32,"h":32},"rotated":false,"trimmed":false,"spriteSourceSize":{"x":0,"y":0,"w":32,"h":32},"sourceSize":{"w":32,"h":32}},"damage_6":{"frame":{"x":256,"y":96,"w":32,"h":32},"rotated":false,"trimmed":false,"spriteSourceSize":{"x":0,"y":0,"w":32,"h":32},"sourceSize":{"w":32,"h":32}},"damage_7":{"frame":{"x":288,"y":96,"w":32,"h":32},"rotated":false,"trimmed":false,"spriteSourceSize":{"x":0,"y":0,"w":32,"h":32},"sourceSize":{"w":32,"h":32}},"health_8":{"frame":{"x":64,"y":128,"w":32,"h":32},"rotated":false,"trimmed":false,"spriteSourceSize":{"x":0,"y":0,"w":32,"h":32},"sourceSize":{"w":32,"h":32}},"health_10":{"frame":{"x":96,"y":128,"w":32,"h":32},"rotated":false,"trimmed":false,"spriteSourceSize":{"x":0,"y":0,"w":32,"h":32},"sourceSize":{"w":32,"h":32}},"health_12":{"frame":{"x":128,"y":128,"w":32,"h":32},"rotated":false,"trimmed":false,"spriteSourceSize":{"x":0,"y":0,"w":32,"h":32},"sourceSize":{"w":32,"h":32}},"health_14":{"frame":{"x":160,"y":128,"w":32,"h":32},"rotated":false,"trimmed":false,"spriteSourceSize":{"x":0,"y":0,"w":32,"h":32},"sourceSize":{"w":32,"h":32}},"damage_8":{"frame":{"x":192,"y":128,"w":32,"h":32},"rotated":false,"trimmed":false,"spriteSourceSize":{"x":0,"y":0,"w":32,"h":32},"sourceSize":{"w":32,"h":32}},"damage_9":{"frame":{"x":224,"y":128,"w":32,"h":32},"rotated":false,"trimmed":false,"spriteSourceSize":{"x":0,"y":0,"w":32,"h":32},"sourceSize":{"w":32,"h":32}},"damage_10":{"frame":{"x":256,"y":128,"w":32,"h":32},"rotated":false,"trimmed":false,"spriteSourceSize":{"x":0,"y":0,"w":32,"h":32},"sourceSize":{"w":32,"h":32}},"damage_11":{"frame":{"x":288,"y":128,"w":32,"h":32},"rotated":false,"trimmed":false,"spriteSourceSize":{"x":0,"y":0,"w":32,"h":32},"sourceSize":{"w":32,"h":32}},"health_1":{"frame":{"x":64,"y":160,"w":32,"h":32},"rotated":false,"trimmed":false,"spriteSourceSize":{"x":0,"y":0,"w":32,"h":32},"sourceSize":{"w":32,"h":32}},"health_3":{"frame":{"x":96,"y":160,"w":32,"h":32},"rotated":false,"trimmed":false,"spriteSourceSize":{"x":0,"y":0,"w":32,"h":32},"sourceSize":{"w":32,"h":32}},"health_5":{"frame":{"x":128,"y":160,"w":32,"h":32},"rotated":false,"trimmed":false,"spriteSourceSize":{"x":0,"y":0,"w":32,"h":32},"sourceSize":{"w":32,"h":32}},"health_7":{"frame":{"x":160,"y":160,"w":32,"h":32},"rotated":false,"trimmed":false,"spriteSourceSize":{"x":0,"y":0,"w":32,"h":32},"sourceSize":{"w":32,"h":32}},"damage_12":{"frame":{"x":192,"y":160,"w":32,"h":32},"rotated":false,"trimmed":false,"spriteSourceSize":{"x":0,"y":0,"w":32,"h":32},"sourceSize":{"w":32,"h":32}},"damage_13":{"frame":{"x":224,"y":160,"w":32,"h":32},"rotated":false,"trimmed":false,"spriteSourceSize":{"x":0,"y":0,"w":32,"h":32},"sourceSize":{"w":32,"h":32}},"damage_14":{"frame":{"x":256,"y":160,"w":32,"h":32},"rotated":false,"trimmed":false,"spriteSourceSize":{"x":0,"y":0,"w":32,"h":32},"sourceSize":{"w":32,"h":32}},"damage_15":{"frame":{"x":288,"y":160,"w":32,"h":32},"rotated":false,"trimmed":false,"spriteSourceSize":{"x":0,"y":0,"w":32,"h":32},"sourceSize":{"w":32,"h":32}},"health_9":{"frame":{"x":64,"y":192,"w":32,"h":32},"rotated":false,"trimmed":false,"spriteSourceSize":{"x":0,"y":0,"w":32,"h":32},"sourceSize":{"w":32,"h":32}},"health_11":{"frame":{"x":96,"y":192,"w":32,"h":32},"rotated":false,"trimmed":false,"spriteSourceSize":{"x":0,"y":0,"w":32,"h":32},"sourceSize":{"w":32,"h":32}},"health_13":{"frame":{"x":128,"y":192,"w":32,"h":32},"rotated":false,"trimmed":false,"spriteSourceSize":{"x":0,"y":0,"w":32,"h":32},"sourceSize":{"w":32,"h":32}},"health_15":{"frame":{"x":160,"y":192,"w":32,"h":32},"rotated":false,"trimmed":false,"spriteSourceSize":{"x":0,"y":0,"w":32,"h":32},"sourceSize":{"w":32,"h":32}}},"meta":{"app":"https://www.leshylabs.com/apps/sstool/","version":"Leshy SpriteSheet Tool v0.8.4","image":"spritesheet.png","size":{"w":350,"h":220},"scale":1}}